etsy_oauth/__init__.py
etsy_oauth/etsy_env.py
etsy_oauth/oauth_client.py
etsy_oauth_zs-0.3.dist-info/METADATA
etsy_oauth_zs-0.3.dist-info/WHEEL
etsy_oauth_zs-0.3.dist-info/top_level.txt
etsy_oauth_zs-0.3.dist-info/RECORD
