Metadata-Version: 2.1
Name: etsy-oauth-zs
Version: 0.3
Summary: UNKNOWN
Home-page: https://github.com/kambag/etsy_api_oauth_zonesmart
Author: Kamil Bagaviev
Author-email: kbagaviev@mail.ru
License: UNKNOWN
Platform: UNKNOWN
Requires-Dist: urllib3 (==1.25.7)
Requires-Dist: oauth2
